tns_energo_api/__init__.py
tns_energo_api/converters.py
tns_energo_api/exceptions.py
tns_energo_api/requests/__init__.py
tns_energo_api/requests/account.py
tns_energo_api/requests/authorization.py
tns_energo_api/requests/get_digital_receipt_status.py
tns_energo_api/requests/get_main_page.py
tns_energo_api/requests/get_payments_page.py
tns_energo_api/requests/get_readings_hist_page.py
tns_energo_api/requests/get_send_indications_page.py
tns_energo_api/requests/send_readings.py
tns_energo_api-0.0.1.dist-info/METADATA
tns_energo_api-0.0.1.dist-info/WHEEL
tns_energo_api-0.0.1.dist-info/top_level.txt
tns_energo_api-0.0.1.dist-info/RECORD
